vkube-2.0.1.dist-info/licenses/LICENSE
vkube_cli/__init__.py
vkube_cli/constants.py
vkube_cli/vkube.py
vkube_cli/command/__init__.py
vkube_cli/command/config.py
vkube_cli/command/version.py
vkube_cli/command/vkube_deploy.py
vkube_cli/docker/__init__.py
vkube_cli/docker/credentials.py
vkube_cli/docker/docker_client.py
vkube_cli/docker_config/__init__.py
vkube_cli/docker_config/credentials.py
vkube_cli/logger/__init__.py
vkube_cli/logger/loading_printer.py
vkube_cli/logger/test_loading_printer.py
vkube_cli/utils/__init__.py
vkube_cli/utils/create_docker_client.py
vkube_cli/utils/decode.py
vkube_cli/utils/file_io.py
vkube_cli/utils/image.py
vkube_cli/utils/ssh.py
vkube_cli/utils/validate_vkubefile.py
vkube_cli/utils/version.py
vkube-2.0.1.dist-info/METADATA
vkube-2.0.1.dist-info/WHEEL
vkube-2.0.1.dist-info/entry_points.txt
vkube-2.0.1.dist-info/top_level.txt
vkube-2.0.1.dist-info/RECORD
