Metadata-Version: 2.4
Name: vkube
Version: 2.0.1
Summary: VKube-CLI User-End
Author: vcloud-team
Author-email: v-cloud-team@v.systems
License: Apache License 2.0
Classifier: License :: OSI Approved :: Apache Software License
Classifier: Programming Language :: Python
Requires-Python: >=3.7
License-File: LICENSE
Requires-Dist: base58==2.1.1
Requires-Dist: blinker==1.9.0
Requires-Dist: certifi==2024.12.14
Requires-Dist: charset-normalizer==3.4.0
Requires-Dist: click==8.1.7
Requires-Dist: docker==7.1.0
Requires-Dist: idna==3.10
Requires-Dist: itsdangerous==2.2.0
Requires-Dist: Jinja2==3.1.5
Requires-Dist: MarkupSafe==3.0.2
Requires-Dist: PyYAML==6.0.2
Requires-Dist: requests==2.32.3
Requires-Dist: setuptools==76.0.0
Requires-Dist: urllib3==2.2.3
Requires-Dist: Werkzeug==3.1.3
Dynamic: author
Dynamic: author-email
Dynamic: classifier
Dynamic: description
Dynamic: description-content-type
Dynamic: license
Dynamic: license-file
Dynamic: requires-dist
Dynamic: requires-python
Dynamic: summary
